{
  "headers": {
    "age": "193",
    "date": "Sat, 09 Jan 2021 21:37:16 GMT",
    "expect-ct": "max-age=604800, report-uri=\"https://report-uri.cloudflare.com/cdn-cgi/beacon/expect-ct\"",
    "nel": "{\"report_to\":\"cf-nel\",\"max_age\":604800}",
    "content-type": "application/javascript",
    "server": "cloudflare",
    "x-amz-id-2": "Oey+x/9aUoZB0duSfWPHAequjBU+9CPq7uYDPWOdNanxKy9rHRXJJiOwqYY1VtyGZZcFEXrvGRw=",
    "vary": "Accept-Encoding",
    "etag": "W/\"d1266ea6a1408f58010346f99e3e0865\"",
    "last-modified": "Sat, 29 Aug 2020 19:56:48 GMT",
    "cf-request-id": "078aae176300002784b2bbb000000001",
    "x-amz-request-id": "872236BF4420EE5D",
    "set-cookie": "__cfduid=d52976eaa6d39864e76f11fb1a2a8e90a1610228236; expires=Mon, 08-Feb-21 21:37:16 GMT; path=/; domain=.deno.land; HttpOnly; SameSite=Lax; Secure",
    "cf-ray": "60f14c6bc93e2784-PRG",
    "cache-control": "public, max-age=31536000, immutable",
    "report-to": "{\"endpoints\":[{\"url\":\"https:\\/\\/a.nel.cloudflare.com\\/report?s=Q0HsunuMu1nH98YmolVZO94ushG2j%2BdVAcxAIhHLJRANC51blhBQAQfA3yZ7sIn9WTB64uBH9XwcGA8sbqZMhoUh%2FdeM3ivGpgQ%3D\"}],\"group\":\"cf-nel\",\"max_age\":604800}",
    "access-control-allow-origin": "*",
    "x-amz-version-id": "null",
    "cf-cache-status": "HIT"
  },
  "url": "https://deno.land/x/lodash@4.17.15-es/assignInWith.js"
}